MANIFEST.in
README.md
requirements.txt
setup.py
text_embedding_model/__init__.py
text_embedding_model/config.py
text_embedding_model/embedding_manager.py
text_embedding_model/input_output_manager.py
text_embedding_model/similarity_manager.py
text_embedding_model/workflow_manager.py
text_embedding_model.egg-info/PKG-INFO
text_embedding_model.egg-info/SOURCES.txt
text_embedding_model.egg-info/dependency_links.txt
text_embedding_model.egg-info/requires.txt
text_embedding_model.egg-info/top_level.txt