Metadata-Version: 2.1
Name: text-embedding-model
Version: 0.3.1
Summary: text_similarity_model
Author: David Yang
Author-email: dongjunyang29@gmail.com
Maintainer: David Yang
Maintainer-email: david.b.yang@au.pwc.com
